dqc/__init__.py
dqc/_version.py
dqc/_version.txt
dqc/api/__init__.py
dqc/api/getxc.py
dqc/api/loadbasis.py
dqc/api/parser.py
dqc/api/properties.py
dqc/datasets/lebedevquad/lebedev_003.txt
dqc/datasets/lebedevquad/lebedev_005.txt
dqc/datasets/lebedevquad/lebedev_007.txt
dqc/datasets/lebedevquad/lebedev_009.txt
dqc/datasets/lebedevquad/lebedev_011.txt
dqc/datasets/lebedevquad/lebedev_013.txt
dqc/datasets/lebedevquad/lebedev_015.txt
dqc/datasets/lebedevquad/lebedev_017.txt
dqc/datasets/lebedevquad/lebedev_019.txt
dqc/datasets/lebedevquad/lebedev_021.txt
dqc/datasets/lebedevquad/lebedev_023.txt
dqc/datasets/lebedevquad/lebedev_025.txt
dqc/datasets/lebedevquad/lebedev_027.txt
dqc/datasets/lebedevquad/lebedev_029.txt
dqc/datasets/lebedevquad/lebedev_031.txt
dqc/datasets/lebedevquad/lebedev_035.txt
dqc/datasets/lebedevquad/lebedev_041.txt
dqc/datasets/lebedevquad/lebedev_047.txt
dqc/datasets/lebedevquad/lebedev_053.txt
dqc/datasets/lebedevquad/lebedev_059.txt
dqc/datasets/lebedevquad/lebedev_065.txt
dqc/datasets/lebedevquad/lebedev_071.txt
dqc/datasets/lebedevquad/lebedev_077.txt
dqc/datasets/lebedevquad/lebedev_083.txt
dqc/datasets/lebedevquad/lebedev_089.txt
dqc/datasets/lebedevquad/lebedev_095.txt
dqc/datasets/lebedevquad/lebedev_101.txt
dqc/datasets/lebedevquad/lebedev_107.txt
dqc/datasets/lebedevquad/lebedev_113.txt
dqc/datasets/lebedevquad/lebedev_119.txt
dqc/datasets/lebedevquad/lebedev_125.txt
dqc/datasets/lebedevquad/lebedev_131.txt
dqc/df/__init__.py
dqc/df/base_df.py
dqc/df/dfmol.py
dqc/df/dfpbc.py
dqc/grid/__init__.py
dqc/grid/base_grid.py
dqc/grid/factory.py
dqc/grid/lebedev_grid.py
dqc/grid/multiatoms_grid.py
dqc/grid/radial_grid.py
dqc/grid/truncation_rules.py
dqc/hamilton/__init__.py
dqc/hamilton/base_hamilton.py
dqc/hamilton/hcgto.py
dqc/hamilton/hcgto_pbc.py
dqc/hamilton/orbconverter.py
dqc/hamilton/intor/__init__.py
dqc/hamilton/intor/gtoeval.py
dqc/hamilton/intor/gtoft.py
dqc/hamilton/intor/lattice.py
dqc/hamilton/intor/lcintwrap.py
dqc-0.1.0.dist-info/LICENSE
dqc-0.1.0.dist-info/METADATA
dqc-0.1.0.dist-info/NOTICE
dqc-0.1.0.dist-info/WHEEL
dqc-0.1.0.dist-info/top_level.txt
dqc-0.1.0.dist-info/RECORD
